python_xycloudsclient-1.0.0.dist-info/DESCRIPTION.rst
python_xycloudsclient-1.0.0.dist-info/METADATA
python_xycloudsclient-1.0.0.dist-info/RECORD
python_xycloudsclient-1.0.0.dist-info/WHEEL
python_xycloudsclient-1.0.0.dist-info/metadata.json
python_xycloudsclient-1.0.0.dist-info/pbr.json
python_xycloudsclient-1.0.0.dist-info/top_level.txt
xycloudsclient/__init__.py
xycloudsclient/adapt_params.py
xycloudsclient/client.py
xycloudsclient/common.py
xycloudsclient/config.ini
xycloudsclient/consolidator.py
xycloudsclient/const.py
xycloudsclient/exceptions.py
xycloudsclient/portal_api_client.py
xycloudsclient/actions/__init__.py
xycloudsclient/actions/alarm.py
xycloudsclient/actions/disk.py
xycloudsclient/actions/host.py
xycloudsclient/actions/network.py
xycloudsclient/actions/security.py
xycloudsclient/actions/user.py
xycloudsclient/actions/vad.py
xycloudsclient/actions/vpn.py
xycloudsclient/actions/woc.py
